odoo/addons/auth_saml_create_user/README.rst
odoo/addons/auth_saml_create_user/__init__.py
odoo/addons/auth_saml_create_user/__manifest__.py
odoo/addons/auth_saml_create_user/data/auth_saml_create_user.xml
odoo/addons/auth_saml_create_user/i18n/auth_saml_create_user.pot
odoo/addons/auth_saml_create_user/models/__init__.py
odoo/addons/auth_saml_create_user/models/auth_saml.py
odoo/addons/auth_saml_create_user/models/res_users.py
odoo/addons/auth_saml_create_user/readme/CONTRIBUTORS.rst
odoo/addons/auth_saml_create_user/readme/CREDITS.rst
odoo/addons/auth_saml_create_user/readme/DESCRIPTION.rst
odoo/addons/auth_saml_create_user/readme/USAGE.rst
odoo/addons/auth_saml_create_user/security/ir.model.access.csv
odoo/addons/auth_saml_create_user/static/description/icon.png
odoo/addons/auth_saml_create_user/static/description/index.html
odoo/addons/auth_saml_create_user/tests/__init__.py
odoo/addons/auth_saml_create_user/tests/arguments.py
odoo/addons/auth_saml_create_user/tests/common.py
odoo/addons/auth_saml_create_user/tests/test_auth_saml_create_users.py
odoo/addons/auth_saml_create_user/views/auth_saml.xml
odoo11_addon_auth_saml_create_user-11.0.1.0.1.dist-info/METADATA
odoo11_addon_auth_saml_create_user-11.0.1.0.1.dist-info/WHEEL
odoo11_addon_auth_saml_create_user-11.0.1.0.1.dist-info/top_level.txt
odoo11_addon_auth_saml_create_user-11.0.1.0.1.dist-info/RECORD
