Metadata-Version: 2.1
Name: odoo11-addon-auth-saml-create-user
Version: 11.0.1.0.1
Summary: This module extends the functionality of Auth SAML to support the automatic creation of SAML users when they don't exist in odoo.
Home-page: https://github.com/OCA/server-auth
Author: Savoir-faire Linux, Odoo Community Association (OCA)
Author-email: support@odoo-community.org
License: AGPL-3
Platform: UNKNOWN
Classifier: Programming Language :: Python
Classifier: Framework :: Odoo
Classifier: License :: OSI Approved :: GNU Affero General Public License v3
Classifier: Development Status :: 5 - Production/Stable
Requires-Python: >=2.7, !=3.0.*, !=3.1.*, !=3.2.*, !=3.3.*, !=3.4.*
Requires-Dist: odoo11-addon-auth-saml
Requires-Dist: odoo (<11.1dev,>=11.0a)
